{"cameraMode":{"drawMode":0,"name":"Shaded","section":"Shading Mode"},"sceneLighting":true,"audioPlay":false,"sceneViewState":{"m_AlwaysRefresh":false,"showFog":true,"showSkybox":true,"showFlares":true,"showImageEffects":true,"showParticleSystems":true,"showVisualEffectGraphs":true,"m_FxEnabled":true},"in2DMode":false,"pivot":{"x":-2.1977148056030275,"y":0.4171144366264343,"z":-1.0728238821029664},"rotation":{"x":-0.0144133809953928,"y":-0.9772272706031799,"z":0.19971951842308045,"w":-0.07048314064741135},"size":6.438027858734131,"orthographic":false}